aiagentgraph/__init__.py
aiagentgraph/langGraphAgent/__init__.py
aiagentgraph/langGraphAgent/graphagent.py
aiagentgraph/langGraphAgent/humanloopagent.py
aiagentgraph/llms/__init__.py
aiagentgraph/llms/models.py
aiagentgraph/simpleReactAgent/__init__.py
aiagentgraph/simpleReactAgent/agent.py
aiagentgraph/simpleReactAgent/agentoptimized.py
aiagentgraph/simpleReactAgent/simpleagent.py
aiagentgraph/simpleReactAgent/tools/agenttools.py
aiagentgraph/tools/__init__.py
aiagentgraph/tools/searchtool.py
aiagentgraph/utils/__init__.py
aiagentgraph/utils/agentutils.py
aiagentgraph-0.0.3.dist-info/METADATA
aiagentgraph-0.0.3.dist-info/WHEEL
aiagentgraph-0.0.3.dist-info/top_level.txt
aiagentgraph-0.0.3.dist-info/RECORD
