Metadata-Version: 2.1
Name: aiagentgraph
Version: 0.0.3
Project-URL: Repository, https://github.com/loaizasteven/AI-Agents-in-LangGraph.git
Requires-Dist: langchain ==0.2.0
Requires-Dist: langchain-community ==0.2.0
Requires-Dist: langchain-openai ==0.1.7
Requires-Dist: langgraph ==0.0.53
Requires-Dist: langsmith ==0.1.93
Requires-Dist: openai ==1.30.1
